Metadata-Version: 2.1
Name: ftpbr
Version: 0.0.1
Summary: A basic  installer
Home-page: UNKNOWN
Author: em
Author-email: 
License: MIT
Keywords: ftpbr
Platform: UNKNOWN
Classifier: Development Status :: 5 - Production/Stable
Classifier: Intended Audience :: Education
Classifier: Operating System :: Microsoft :: Windows :: Windows 10
Classifier: License :: OSI Approved :: MIT License
Classifier: Programming Language :: Python :: 3
